README
setup.py
virtualenv_tools.py
virtualenv_tools.egg-info/PKG-INFO
virtualenv_tools.egg-info/SOURCES.txt
virtualenv_tools.egg-info/dependency_links.txt
virtualenv_tools.egg-info/entry_points.txt
virtualenv_tools.egg-info/not-zip-safe
virtualenv_tools.egg-info/top_level.txt