Metadata-Version: 1.1
Name: virtualenv-tools
Version: 1.0
Summary: A set of tools for virtualenv
Home-page: http://github.com/fireteam/virtualenv-tools
Author: Fireteam Ltd.
Author-email: support@fireteam.net
License: UNKNOWN
Platform: UNKNOWN
Classifier: License :: OSI Approved :: BSD License
Classifier: Programming Language :: Python
